Metadata-Version: 2.1
Name: BWIAICalculator1
Version: 0.0.1
Summary: A basic calculator
Home-page: UNKNOWN
Author: Angle Bush
Author-email: contact@blackwomeninai.com
License: MIT
Keywords: calculator
Platform: UNKNOWN
Classifier: Development Status :: 5 - Production/Stable
Classifier: Intended Audience :: Education
Classifier: Operating System :: Microsoft :: Windows :: Windows 10
Classifier: License :: OSI Approved :: MIT License
Classifier: Programming Language :: Python :: 3
License-File: LICENSE.txt
